Jiangziyi/Jiangziyi.py
Jiangziyi/__init__.py
Jiangziyi-0.0.3.dist-info/METADATA
Jiangziyi-0.0.3.dist-info/WHEEL
Jiangziyi-0.0.3.dist-info/top_level.txt
Jiangziyi-0.0.3.dist-info/RECORD
